{"count":8,"ringList":[{"name":"致爱利丝","desc":"致爱利丝","url":"ringing/category/6/1/致爱利丝.mp3","length":604620},{"name":"这个铃声听了后，清凉爽","desc":"这个铃声听了后，清凉爽","url":"ringing/category/6/1/这个铃声听了后，清凉爽.mp3","length":77941},{"name":"这个铃声听了后，让人有种清凉的感觉，啊………………爽","desc":"这个铃声听了后，让人有种清凉的感觉，啊………………爽","url":"ringing/category/6/1/这个铃声听了后，让人有种清凉的感觉，啊………………爽.mp3","length":183213},{"name":"震撼全世界的手机铃声[1][1].php","desc":"震撼全世界的手机铃声[1][1].php","url":"ringing/category/6/1/震撼全世界的手机铃声[1][1].php.mp3","length":717360},{"name":"震撼全世界的铃声(高潮版）","desc":"震撼全世界的铃声(高潮版）","url":"ringing/category/6/1/震撼全世界的铃声(高潮版）.mp3","length":717468},{"name":"震撼全世界的铃声(高潮版）黑客帝国","desc":"震撼全世界的铃声(高潮版）黑客帝国","url":"ringing/category/6/1/震撼全世界的铃声(高潮版）黑客帝国.mp3","length":717468},{"name":"震撼全世界的铃声","desc":"震撼全世界的铃声","url":"ringing/category/6/1/震撼全世界的铃声.mp3","length":135721},{"name":"震撼鼓音","desc":"震撼鼓音","url":"ringing/category/6/1/震撼鼓音.mp3","length":72901}]}